odoo/addons/base_repair_config/README.rst
odoo/addons/base_repair_config/__init__.py
odoo/addons/base_repair_config/__manifest__.py
odoo/addons/base_repair_config/i18n/base_repair_config.pot
odoo/addons/base_repair_config/i18n/it.po
odoo/addons/base_repair_config/i18n/pt_BR.po
odoo/addons/base_repair_config/readme/CONFIGURE.rst
odoo/addons/base_repair_config/readme/CONTRIBUTORS.rst
odoo/addons/base_repair_config/readme/DESCRIPTION.rst
odoo/addons/base_repair_config/readme/USAGE.rst
odoo/addons/base_repair_config/static/description/banner.png
odoo/addons/base_repair_config/static/description/icon.png
odoo/addons/base_repair_config/static/description/index.html
odoo/addons/base_repair_config/views/res_config_settings.xml
odoo13_addon_base_repair_config-13.0.1.0.1.dev7.dist-info/METADATA
odoo13_addon_base_repair_config-13.0.1.0.1.dev7.dist-info/WHEEL
odoo13_addon_base_repair_config-13.0.1.0.1.dev7.dist-info/top_level.txt
odoo13_addon_base_repair_config-13.0.1.0.1.dev7.dist-info/RECORD
